dh_facebook_client/__init__.py
dh_facebook_client/client.py
dh_facebook_client/constants.py
dh_facebook_client/dataclasses.py
dh_facebook_client/error_code.py
dh_facebook_client/exceptions.py
dh_facebook_client/helpers.py
dh_facebook_client/typings.py
dh_facebook_client-0.7.1.dist-info/METADATA
dh_facebook_client-0.7.1.dist-info/WHEEL
dh_facebook_client-0.7.1.dist-info/RECORD
