Metadata-Version: 2.4
Name: dh-facebook-client
Version: 0.7.1
Summary: Simple client for interacting with the Facebook Graph API
Author: pchisholm
Author-email: chisholm.p@gmail.com
Requires-Python: >=3.9,<4.0
Classifier: Programming Language :: Python :: 3
Classifier: Programming Language :: Python :: 3.9
Classifier: Programming Language :: Python :: 3.10
Classifier: Programming Language :: Python :: 3.11
Classifier: Programming Language :: Python :: 3.12
Classifier: Programming Language :: Python :: 3.13
Classifier: Programming Language :: Python :: 3.14
Requires-Dist: backoff (>=1.11.1,<2.0.0)
Requires-Dist: requests (>=2.26.0,<3.0.0)
